aioaprs/__init__.py
aioaprs/client.py
aioaprs/config.py
aioaprs/default.py
aioaprs/packets.py
aioaprs/parser.py
aioaprs/serializer.py
aioaprs/version.py
aioaprs/enrichers/__init__.py
aioaprs/enrichers/telemetry.py
aioaprs/parsers/__init__.py
aioaprs/parsers/message.py
aioaprs/parsers/telemetry.py
aioaprs/serializers/__init__.py
aioaprs/serializers/telemetry.py
aioaprs-0.4.2.dist-info/LICENSE.md
aioaprs-0.4.2.dist-info/METADATA
aioaprs-0.4.2.dist-info/WHEEL
aioaprs-0.4.2.dist-info/top_level.txt
aioaprs-0.4.2.dist-info/RECORD
